copypastor/__init__.py
copypastor/copypastor.py
copypastor/config/__init__.py
copypastor/config/default_config.py
copypastor/src/__init__.py
copypastor/src/client.py
copypastor/src/server.py
copypastor-1.0.3.dist-info/LICENSE.md
copypastor-1.0.3.dist-info/METADATA
copypastor-1.0.3.dist-info/WHEEL
copypastor-1.0.3.dist-info/entry_points.txt
copypastor-1.0.3.dist-info/top_level.txt
copypastor-1.0.3.dist-info/RECORD
