Metadata-Version: 2.1
Name: copypastor
Version: 1.0.3
Summary: For clipboard copy/paste remote action ;-)
Home-page: https://github.com/Venomen/copypastor
Author: Dawid Deręgowski
Author-email: dawid@deregowski.net
License: MIT
Platform: UNKNOWN
Classifier: Programming Language :: Python :: 3
Classifier: License :: OSI Approved :: MIT License
Classifier: Operating System :: OS Independent
License-File: LICENSE.md
Requires-Dist: emoji (==1.6.3)
Requires-Dist: pyperclip (==1.8.2)
Requires-Dist: pynput (==1.7.6)
